{
  "btc_spot_usd": 87188.34,
  "derivatives_okx": {
    "fundingRate": 7.274430772e-07,
    "fundingTime": 1766793600000,
    "instId": "BTC-USDT-SWAP",
    "method": "current_period",
    "nextFundingTime": 1766822400000,
    "premium": -0.000554671849716,
    "ts": 1766774582292
  },
  "levels": {
    "resistance": [
      88496.16
    ],
    "support": [
      85880.51
    ]
  },
  "paper_test_trade": {
    "long": {
      "entry": 87449.9,
      "stop": 85708.75,
      "tps": [
        88060.22,
        88496.16
      ],
      "trigger": "15m close >= 87362.71"
    },
    "short": {
      "entry": 86926.77,
      "stop": 88673.15,
      "tps": [
        86316.45,
        85880.51
      ],
      "trigger": "15m close <= 87013.96"
    },
    "test_trade_id": "BTC-2025-12-26-0600-ET-TEST",
    "type": "OCO_conditional"
  },
  "prior_day_review": {
    "note": "Upgrade path: pull candles and auto-score whether triggers fired + MAE/MFE for yesterday.",
    "status": "not_implemented"
  },
  "risk_rules": {
    "daily_stop_R": 2.0,
    "funding_half_size_threshold": 0.0003,
    "funding_no_trade_threshold": 0.001,
    "max_risk_per_idea_R": 1.0
  },
  "run_timestamp_et": "2025-12-26 13:43"
}
